[
 {
  "item": "샤넬 디올 가방들 정리합니다",
  "price": "100원",
  "region": "부산 해운대구 우제2동",
  "like": 112,
  "chat": 63,
  "image": "images\/bs\/bsimg0.jpg"
 },
 {
  "item": "크록스 새제품팝니다",
  "price": "28,000원",
  "region": "부산 기장군 정관읍",
  "like": 14,
  "chat": 39,
  "image": "images\/bs\/bsimg1.jpg"
 },
 {
  "item": "가져가주세요ㅠㅠ",
  "price": "5,000원",
  "region": "부산 서구 암남동",
  "like": 12,
  "chat": 7,
  "image": "images\/bs\/bsimg2.jpg"
 },
 {
  "item": "이사가면서 가전정리합니다(세탁기,장농 밥솥장 건조기)",
  "price": "30,000원",
  "region": "부산 수영구 망미제2동",
  "like": 16,
  "chat": 23,
  "image": "images\/bs\/bsimg3.jpg"
 },
 {
  "item": "보아르 제습기",
  "price": "50,000원",
  "region": "부산 부산진구 범천동",
  "like": 8,
  "chat": 12,
  "image": "images\/bs\/bsimg4.jpg"
 },
 {
  "item": "백태콩,검은콩",
  "price": "10,000원",
  "region": "부산 북구 금곡동",
  "like": 3,
  "chat": 11,
  "image": "images\/bs\/bsimg5.jpg"
 },
 {
  "item": "베트남 동 판매합니다",
  "price": "197,000원",
  "region": "부산 남구 대연제3동",
  "like": 9,
  "chat": 13,
  "image": "images\/bs\/bsimg6.jpg"
 },
 {
  "item": "헌터 레인부츠",
  "price": "160,000원",
  "region": "부산 남구 대연제1동",
  "like": 17,
  "chat": 20,
  "image": "images\/bs\/bsimg7.jpg"
 },
 {
  "item": "이케아 점포정리",
  "region": "부산 강서구 명지2동",
  "like": 27,
  "chat": 25,
  "image": "images\/bs\/bsimg8.jpg"
 },
 {
  "item": "5단렉선반",
  "price": "20,000원",
  "region": "부산 동래구 사직동",
  "like": 12,
  "chat": 10,
  "image": "images\/bs\/bsimg9.jpg"
 },
 {
  "item": "sk매직 전자레인지",
  "price": "20,000원",
  "region": "부산 연제구 연산동",
  "like": 4,
  "chat": 7,
  "image": "images\/bs\/bsimg10.jpg"
 },
 {
  "item": "삼성공기청정기",
  "price": "20,000원",
  "region": "부산 부산진구 부암제3동",
  "like": 4,
  "chat": 5,
  "image": "images\/bs\/bsimg11.jpg"
 },
 {
  "item": "참기름",
  "price": "3,000원",
  "region": "부산 남구 대연제6동",
  "like": 11,
  "chat": 30,
  "image": "images\/bs\/bsimg12.jpg"
 },
 {
  "item": "베베드피노 모자",
  "price": "15,000원",
  "region": "부산 부산진구 당감동",
  "like": 1,
  "chat": 13,
  "image": "images\/bs\/bsimg13.jpg"
 },
 {
  "item": "접이식 자전거",
  "price": "10,000원",
  "region": "부산 해운대구 우동",
  "like": 6,
  "chat": 8,
  "image": "images\/bs\/bsimg14.jpg"
 },
 {
  "item": "에어팟 프로2",
  "price": "80,000원",
  "region": "부산 수영구 망미동",
  "like": 12,
  "chat": 11,
  "image": "images\/bs\/bsimg15.jpg"
 },
 {
  "item": "갤럭시 S21",
  "price": "280,000원",
  "region": "부산 부산진구 가야제1동",
  "like": 6,
  "chat": 7,
  "image": "images\/bs\/bsimg16.jpg"
 },
 {
  "item": "SK매직 식기세척기 6인용",
  "price": "10,000원",
  "region": "부산 서구 서대신제3동",
  "like": 15,
  "chat": 15,
  "image": "images\/bs\/bsimg17.jpg"
 },
 {
  "item": "워치5 40미리 골프에디션",
  "price": "150,000원",
  "region": "부산 부산진구 부전동",
  "like": 6,
  "chat": 11,
  "image": "images\/bs\/bsimg18.jpg"
 },
 {
  "item": "lg코드제로 청소기",
  "price": "40,000원",
  "region": "부산 북구 구포동",
  "like": 11,
  "chat": 1,
  "image": "images\/bs\/bsimg19.jpg"
 },
 {
  "item": "베트남 동 팔아요",
  "price": "106,000원",
  "region": "부산 동래구 명장제1동",
  "like": 2,
  "chat": 10,
  "image": "images\/bs\/bsimg20.jpg"
 },
 {
  "item": "먹태깡 새거 정가 판매합니다",
  "price": "1,700원",
  "region": "부산 부산진구 전포동",
  "like": 6,
  "chat": 7,
  "image": "images\/bs\/bsimg21.jpg"
 },
 {
  "item": "다이슨 공기청정기",
  "price": "100,000원",
  "region": "부산 동래구 온천동",
  "like": 9,
  "chat": 5,
  "image": "images\/bs\/bsimg22.jpg"
 },
 {
  "item": "테라스 파라솔+라탄테이블+의자",
  "price": "130,000원",
  "region": "부산 강서구 명지1동",
  "like": 21,
  "chat": 2,
  "image": "images\/bs\/bsimg23.jpg"
 },
 {
  "item": "원도우냉장고",
  "price": "100,000원",
  "region": "부산 연제구 거제동",
  "like": 5,
  "chat": 11,
  "image": "images\/bs\/bsimg24.jpg"
 },
 {
  "item": "위닉스 제습기 17L 팝니다",
  "price": "230,000원",
  "region": "부산 부산진구 개금제3동",
  "like": 7,
  "chat": 7,
  "image": "images\/bs\/bsimg25.jpg"
 },
 {
  "item": "롯데 제습기",
  "price": "90,000원",
  "region": "부산 부산진구 부전동",
  "like": 1,
  "chat": 10,
  "image": "images\/bs\/bsimg26.jpg"
 },
 {
  "item": "쌀 팔아요",
  "price": "6,000원",
  "region": "부산 부산진구 연지동",
  "like": 1,
  "chat": 7,
  "image": "images\/bs\/bsimg27.jpg"
 },
 {
  "item": "5단선반",
  "price": "5,000원",
  "region": "부산 동구 초량동",
  "like": 10,
  "chat": 13,
  "image": "images\/bs\/bsimg28.jpg"
 },
 {
  "item": "lg 65인치 tv  부품용\/수리해서 쓰실 분",
  "price": "10,000원",
  "region": "부산 동구 범일동",
  "like": 8,
  "chat": 5,
  "image": "images\/bs\/bsimg29.jpg"
 },
 {
  "item": "스텔스2  3번우드",
  "price": "90,000원",
  "region": "부산 북구 구포동",
  "like": 8,
  "chat": 3,
  "image": "images\/bs\/bsimg30.jpg"
 },
 {
  "item": "젝시오11 xxio 여자골프채 아이언세트(mp1100)",
  "price": "270,000원",
  "region": "부산 연제구 연산동",
  "like": 25,
  "chat": 2,
  "image": "images\/bs\/bsimg31.jpg"
 },
 {
  "item": "삼성 43인치 티비 팝니다",
  "price": "150,000원",
  "region": "부산 해운대구 좌동",
  "like": 14,
  "chat": 11,
  "image": "images\/bs\/bsimg32.jpg"
 },
 {
  "item": "파김치 2.5kg",
  "price": "10,000원",
  "region": "부산 부산진구 전포동",
  "like": 4,
  "chat": 4,
  "image": "images\/bs\/bsimg33.jpg"
 },
 {
  "item": "프라다 woc 루비노",
  "price": "300,000원",
  "region": "부산 해운대구 재송제1동",
  "like": 24,
  "chat": 5,
  "image": "images\/bs\/bsimg34.jpg"
 },
 {
  "item": "위닉스 10리터 제습기",
  "price": "90,000원",
  "region": "부산 연제구 연산제9동",
  "like": 9,
  "chat": 7,
  "image": "images\/bs\/bsimg35.jpg"
 },
 {
  "item": "에어컨 냉난방기 팔아요 철거",
  "region": "부산 동래구 온천제1동",
  "like": 4,
  "chat": 16,
  "image": "images\/bs\/bsimg36.jpg"
 },
 {
  "item": "에어컨 필요하신분",
  "price": "50,000원",
  "region": "부산 사하구 감천동",
  "like": 2,
  "chat": 5,
  "image": "images\/bs\/bsimg37.jpg"
 },
 {
  "item": "여자 버버리 패딩 (완벽 깨끗 최상급 상태)",
  "price": "480,000원",
  "region": "부산 연제구 거제동",
  "like": 11,
  "chat": 4,
  "image": "images\/bs\/bsimg38.jpg"
 },
 {
  "item": "크로우 도쿄나인 미니벨로 접이식자전거",
  "price": "100,000원",
  "region": "부산 수영구 망미동",
  "like": 13,
  "chat": 3,
  "image": "images\/bs\/bsimg39.jpg"
 },
 {
  "item": "위닉스 제습기 10L팔아요",
  "price": "150,000원",
  "region": "부산 북구 덕천동",
  "like": 90,
  "chat": 80,
  "image": "images\/bs\/bsimg40.jpg"
 },
 {
  "item": "딥디크 롬브르단도 퍼퓸 (2023.07.07)",
  "price": "30,000원",
  "region": "부산 남구 대연제3동",
  "like": 5,
  "chat": 3,
  "image": "images\/bs\/bsimg41.jpg"
 },
 {
  "item": "삼성전자레인지",
  "price": "15,000원",
  "region": "부산 중구 대청동",
  "like": 1,
  "chat": 11,
  "image": "images\/bs\/bsimg42.jpg"
 },
 {
  "item": "18k 금팔찌 팝니다",
  "price": "235,000원",
  "region": "부산 수영구 망미제1동",
  "like": 4,
  "chat": 9,
  "image": "images\/bs\/bsimg43.jpg"
 },
 {
  "item": "보다나 판고데기",
  "price": "15,000원",
  "region": "부산 연제구 거제제3동",
  "like": 6,
  "chat": 8,
  "image": "images\/bs\/bsimg44.jpg"
 },
 {
  "item": "캠핑 테이블",
  "price": "3,000원",
  "region": "부산 동구 초량동",
  "like": 6,
  "chat": 4,
  "image": "images\/bs\/bsimg45.jpg"
 },
 {
  "item": "영아다중",
  "price": "20,000원",
  "region": "부산 해운대구 우동",
  "like": 2,
  "chat": 6,
  "image": "images\/bs\/bsimg46.jpg"
 },
 {
  "item": "3단 선반 판매합니다",
  "price": "5,000원",
  "region": "부산 연제구 연산제1동",
  "like": 9,
  "chat": 8,
  "image": "images\/bs\/bsimg47.jpg"
 },
 {
  "item": "파파야나인 포르쉐 푸쉬카",
  "price": "40,000원",
  "region": "부산 사하구 다대제1동",
  "like": 4,
  "chat": 8,
  "image": "images\/bs\/bsimg48.jpg"
 },
 {
  "item": "캐리어 10평형 에어컨 판매[5만]",
  "price": "50,000원",
  "region": "부산 부산진구 당감제4동",
  "like": 2,
  "chat": 16,
  "image": "images\/bs\/bsimg49.jpg"
 },
 {
  "item": "인조잔디, 잔디매트",
  "price": "15,000원",
  "region": "부산 부산진구 부전제2동",
  "like": 10,
  "chat": 9,
  "image": "images\/bs\/bsimg50.jpg"
 },
 {
  "item": "발렌시아가 후드티 사이즈 L",
  "price": "150,000원",
  "region": "부산 북구 만덕동",
  "like": 18,
  "chat": 18,
  "image": "images\/bs\/bsimg51.jpg"
 },
 {
  "item": "헌터 레인부츠 37 사이즈",
  "price": "30,000원",
  "region": "부산 북구 화명동",
  "like": 3,
  "chat": 6,
  "image": "images\/bs\/bsimg52.jpg"
 },
 {
  "item": "이케아 레르베리 남색 철제 선반",
  "price": "17,000원",
  "region": "부산 연제구 연산제8동",
  "like": 3,
  "chat": 3,
  "image": "images\/bs\/bsimg53.jpg"
 },
 {
  "item": "위니아 제습기",
  "price": "100,000원",
  "region": "부산 남구 대연동",
  "like": 4,
  "chat": 12,
  "image": "images\/bs\/bsimg54.jpg"
 },
 {
  "item": "삼성 무선청소기",
  "price": "30,000원",
  "region": "부산 연제구 연산동",
  "like": 14,
  "chat": 9,
  "image": "images\/bs\/bsimg55.jpg"
 },
 {
  "item": "롯데워터파크 골드시즌 종일권팝니다 2인단위",
  "price": "35,000원",
  "region": "부산 강서구 명지2동",
  "like": 25,
  "chat": 23,
  "image": "images\/bs\/bsimg56.jpg"
 },
 {
  "item": "아난티 힐튼 부산",
  "price": "300,000원",
  "region": "부산 동래구 수민동",
  "like": 18,
  "chat": 8,
  "image": "images\/bs\/bsimg57.jpg"
 },
 {
  "item": "베베드피노모자",
  "price": "10,000원",
  "region": "부산 사상구 괘법동",
  "like": 1,
  "chat": 8,
  "image": "images\/bs\/bsimg58.jpg"
 },
 {
  "item": "장농판매합니다",
  "price": "50,000원",
  "region": "부산 연제구 연산제9동",
  "like": 3,
  "chat": 4,
  "image": "images\/bs\/bsimg59.jpg"
 },
 {
  "item": "전자렌지",
  "price": "20,000원",
  "region": "부산 동래구 명륜동",
  "like": 16,
  "chat": 12,
  "image": "images\/bs\/bsimg60.jpg"
 },
 {
  "item": "조말론 향수, 존 바바토스",
  "price": "10,000원",
  "region": "부산 남구 대연동",
  "like": 4,
  "chat": 5,
  "image": "images\/bs\/bsimg61.jpg"
 },
 {
  "item": "투명 접의식 의자 팝니다~~!!",
  "price": "10,000원",
  "region": "부산 북구 덕천제2동",
  "like": 10,
  "chat": 13,
  "image": "images\/bs\/bsimg62.jpg"
 },
 {
  "item": "이사해서 정리합니다.",
  "price": "30,000원",
  "region": "부산 서구 남부민동",
  "like": 2,
  "chat": 2,
  "image": "images\/bs\/bsimg63.jpg"
 },
 {
  "item": "위닉스 제습기",
  "price": "160,000원",
  "region": "부산 부산진구 연지동",
  "like": 7,
  "chat": 4,
  "image": "images\/bs\/bsimg64.jpg"
 },
 {
  "item": "선풍기 팝니다",
  "price": "10,000원",
  "region": "부산 해운대구 우제3동",
  "like": 5,
  "chat": 10,
  "image": "images\/bs\/bsimg65.jpg"
 },
 {
  "item": "싸게팝니다",
  "price": "1원",
  "region": "부산 연제구 연산제8동",
  "like": 5,
  "chat": 7,
  "image": "images\/bs\/bsimg66.jpg"
 },
 {
  "item": "두나 리크 트라이크 세발자전거 (로얄블루)",
  "price": "50,000원",
  "region": "부산 해운대구 재송제1동",
  "like": 4,
  "chat": 6,
  "image": "images\/bs\/bsimg67.jpg"
 },
 {
  "item": "리안 바구니카시트",
  "price": "10,000원",
  "region": "부산 부산진구 범천동",
  "like": 7,
  "chat": 6,
  "image": "images\/bs\/bsimg68.jpg"
 },
 {
  "item": "《이사처분》LG디오스 스탠드 김치냉장고",
  "price": "380,000원",
  "region": "부산 북구 화명제1동",
  "like": 7,
  "chat": 3,
  "image": "images\/bs\/bsimg69.jpg"
 },
 {
  "item": "프뢰벨 영아다중",
  "price": "80,000원",
  "region": "부산 수영구 수영동",
  "like": 1,
  "chat": 6,
  "image": "images\/bs\/bsimg70.jpg"
 },
 {
  "item": "갤럭시 노트10 판매합니다",
  "price": "150,000원",
  "region": "부산 부산진구 부암동",
  "like": 6,
  "chat": 4,
  "image": "images\/bs\/bsimg71.jpg"
 },
 {
  "item": "압력솥",
  "price": "18,000원",
  "region": "부산 강서구 명지동",
  "like": 5,
  "chat": 3,
  "image": "images\/bs\/bsimg72.jpg"
 },
 {
  "item": "식당 업소용 싱크대 판매 (사이즈 많음)",
  "price": "30,000원",
  "region": "부산 연제구 거제동",
  "like": 44,
  "chat": 32,
  "image": "images\/bs\/bsimg73.jpg"
 },
 {
  "item": "미니제습기팝니다",
  "price": "30,000원",
  "region": "부산 부산진구 초읍동",
  "like": 3,
  "chat": 3,
  "image": "images\/bs\/bsimg74.jpg"
 },
 {
  "item": "원목테이블과 의자",
  "price": "10,000원",
  "region": "부산 남구 대연제6동",
  "like": 12,
  "chat": 9,
  "image": "images\/bs\/bsimg75.jpg"
 },
 {
  "item": "냉장고",
  "price": "50,000원",
  "region": "부산 기장군 정관읍",
  "like": 5,
  "chat": 8,
  "image": "images\/bs\/bsimg76.jpg"
 },
 {
  "item": "선풍기",
  "price": "10원",
  "region": "부산 강서구 명지2동",
  "like": 2,
  "chat": 5,
  "image": "images\/bs\/bsimg77.jpg"
 },
 {
  "item": "퓨어코치 미니제습기",
  "price": "14,000원",
  "region": "부산 기장군 일광읍",
  "like": 4,
  "chat": 4,
  "image": "images\/bs\/bsimg78.jpg"
 },
 {
  "item": "BMW보스턴백 새거",
  "price": "20,000원",
  "region": "부산 강서구 명지동",
  "like": 5,
  "chat": 4,
  "image": "images\/bs\/bsimg79.jpg"
 },
 {
  "item": "추피의 생활동화 세이펜 버전",
  "price": "60,000원",
  "region": "부산 사하구 괴정동",
  "like": 1,
  "chat": 7,
  "image": "images\/bs\/bsimg80.jpg"
 },
 {
  "item": "LG 제습기",
  "price": "100,000원",
  "region": "부산 영도구 동삼제1동",
  "like": 0,
  "chat": 3,
  "image": "images\/bs\/bsimg81.jpg"
 },
 {
  "item": "LG 엘지 냉장고 237L",
  "price": "150,000원",
  "region": "부산 부산진구 전포제2동",
  "like": 3,
  "chat": 6,
  "image": "images\/bs\/bsimg82.jpg"
 },
 {
  "item": "금값만받아요",
  "region": "부산 서구 서대신동1가",
  "like": 8,
  "chat": 13,
  "image": "images\/bs\/bsimg83.jpg"
 },
 {
  "item": "추피 생활이야기 70권 세이펜버전",
  "price": "75,000원",
  "region": "부산 사상구 괘법동",
  "like": 6,
  "chat": 7,
  "image": "images\/bs\/bsimg84.jpg"
 },
 {
  "item": "18k 반지",
  "price": "270,000원",
  "region": "부산 부산진구 전포제2동",
  "like": 7,
  "chat": 6,
  "image": "images\/bs\/bsimg85.jpg"
 },
 {
  "item": "TV 티비  58인치",
  "price": "120,000원",
  "region": "부산 동래구 온천제1동",
  "like": 10,
  "chat": 4,
  "image": "images\/bs\/bsimg86.jpg"
 },
 {
  "item": "휘슬러 냄비 셋  팔아요",
  "price": "100,000원",
  "region": "부산 남구 용호동",
  "like": 12,
  "chat": 1,
  "image": "images\/bs\/bsimg87.jpg"
 },
 {
  "item": "코아존 보닉 고압세척기",
  "price": "80,000원",
  "region": "부산 동구 범일동",
  "like": 5,
  "chat": 3,
  "image": "images\/bs\/bsimg88.jpg"
 },
 {
  "item": "디엘티 65인치 LED TV",
  "price": "200,000원",
  "region": "부산 동구 수정동",
  "like": 8,
  "chat": 5,
  "image": "images\/bs\/bsimg89.jpg"
 },
 {
  "item": "삼성Tv 45인치",
  "region": "부산 동래구 온천제2동",
  "like": 5,
  "chat": 7,
  "image": "images\/bs\/bsimg90.jpg"
 },
 {
  "item": "긴급!! 쌀떡볶이떡 팝니다ㅠㅠ",
  "price": "7,000원",
  "region": "부산 해운대구 우동",
  "like": 30,
  "chat": 11,
  "image": "images\/bs\/bsimg91.jpg"
 },
 {
  "item": "자동차 자가정비 할때 쓰던 공구들 일괄정리 합니다.",
  "price": "30,000원",
  "region": "부산 수영구 광안제2동",
  "like": 4,
  "chat": 2,
  "image": "images\/bs\/bsimg92.jpg"
 },
 {
  "item": "콜라!! 가져가세요^^",
  "price": "8,000원",
  "region": "부산 부산진구 범천제1동",
  "like": 7,
  "chat": 5,
  "image": "images\/bs\/bsimg93.jpg"
 },
 {
  "item": "셀린느 에코백 스트라이프 에코백",
  "price": "60,000원",
  "region": "부산 연제구 연산제2동",
  "like": 63,
  "chat": 6,
  "image": "images\/bs\/bsimg94.jpg"
 },
 {
  "item": "크록스 260",
  "price": "28,000원",
  "region": "부산 해운대구 우제1동",
  "like": 7,
  "chat": 7,
  "image": "images\/bs\/bsimg95.jpg"
 }
]